hagelslag/VERSION
hagelslag/__init__.py
hagelslag/data/FV3ModelGrid.py
hagelslag/data/GribModelGrid.py
hagelslag/data/HREFv2ModelGrid.py
hagelslag/data/HRRREModelGrid.py
hagelslag/data/HRRRModelGrid.py
hagelslag/data/HRRRZarrModelGrid.py
hagelslag/data/HailForecastGrid.py
hagelslag/data/MPASHrrrGrid.py
hagelslag/data/MRMSGrid.py
hagelslag/data/ModelGrid.py
hagelslag/data/ModelOutput.py
hagelslag/data/NCARModelGrid.py
hagelslag/data/NCARStormEventModelGrid.py
hagelslag/data/NCARWRF2020ModelGrid.py
hagelslag/data/SSEFModelGrid.py
hagelslag/data/VSEModelGrid.py
hagelslag/data/WRFModelGrid.py
hagelslag/data/ZarrModelGrid.py
hagelslag/data/__init__.py
hagelslag/evaluation/ContingencyTable.py
hagelslag/evaluation/GridEvaluator.py
hagelslag/evaluation/MetricPlotter.py
hagelslag/evaluation/MulticlassContingencyTable.py
hagelslag/evaluation/NeighborEvaluator.py
hagelslag/evaluation/ObjectEvaluator.py
hagelslag/evaluation/ProbabilityMetrics.py
hagelslag/evaluation/__init__.py
hagelslag/mapfiles/GRIB2Table_hrrr_2d.csv
hagelslag/mapfiles/GRIB2Table_hrrr_nat.csv
hagelslag/mapfiles/README
hagelslag/mapfiles/VSE.txt
hagelslag/mapfiles/VSE_mask.nc
hagelslag/mapfiles/gridparms.rst
hagelslag/mapfiles/hrefv2_2018_map.txt
hagelslag/mapfiles/hrefv2_us_mask.nc
hagelslag/mapfiles/hrefv2_us_mask_djg.nc
hagelslag/mapfiles/hrrr_grib.csv
hagelslag/mapfiles/hrrr_map_2016.txt
hagelslag/mapfiles/hrrr_params_grib2_tbl_new.txt
hagelslag/mapfiles/hrrre_2019_map.txt
hagelslag/mapfiles/hrrre_us_mask.nc
hagelslag/mapfiles/mpas_interp_hrrr_map_2023.txt
hagelslag/mapfiles/ncar_2015_us_mask.nc
hagelslag/mapfiles/ncar_ensemble_map_2013.txt
hagelslag/mapfiles/ncar_ensemble_map_2015.txt
hagelslag/mapfiles/ncar_grib_table.txt
hagelslag/mapfiles/ncar_storm_map_1km.txt
hagelslag/mapfiles/ncar_storm_map_3km.txt
hagelslag/mapfiles/ncar_storm_us_mask_1km.nc
hagelslag/mapfiles/ncar_storm_us_mask_3km.nc
hagelslag/mapfiles/ssef2013.map
hagelslag/mapfiles/ssef2014.map
hagelslag/mapfiles/ssef2015.map
hagelslag-0.6.dist-info/LICENSE.txt
hagelslag-0.6.dist-info/METADATA
hagelslag-0.6.dist-info/WHEEL
hagelslag-0.6.dist-info/top_level.txt
hagelslag-0.6.dist-info/RECORD
