Metadata-Version: 2.1
Name: hagelslag
Version: 0.6
Summary: Hagelslag is a Python package for storm-based analysis, forecasting, and evaluation.
Author-email: David John Gagne <dgagne@ucar.edu>
Keywords: hail,verification,tracking,weather,meteorology,machine learning
Classifier: Development Status :: 5 - Production/Stable
Classifier: Intended Audience :: Science/Research
Classifier: License :: OSI Approved :: MIT License
Classifier: Programming Language :: Python :: 3
Classifier: Programming Language :: Python :: 3.7
Classifier: Programming Language :: Python :: 3.8
Classifier: Programming Language :: Python :: 3.9
Classifier: Programming Language :: Python :: 3.10
Classifier: Programming Language :: Python :: 3.11
Requires-Python: >=3.7
License-File: LICENSE.txt
Requires-Dist: numpy
Requires-Dist: scipy
Requires-Dist: matplotlib
Requires-Dist: xarray
Requires-Dist: pandas
Requires-Dist: scikit-image
Requires-Dist: scikit-learn
Requires-Dist: dask
Requires-Dist: zarr
Requires-Dist: numba
Requires-Dist: pygrib
Requires-Dist: pyproj
Requires-Dist: pyarrow
Requires-Dist: pyshp
